[
  {
    "id": 1,
    "name": "Vyvyan Holland",
    "username": "vyvyan.holland",
    "state": "active",
    "access_level": 30
  },
  {
    "id": 2,
    "name": "Bob Burger",
    "username": "bob.burger",
    "state": "active",
    "access_level": 30
  },
  {
    "id": 3,
    "name": "Tina Belcher",
    "username": "tina.belcher",
    "state": "active",
    "access_level": 40
  },
  {
    "id": 4,
    "name": "Gene Belcher",
    "username": "gene.belcher",
    "state": "active",
    "access_level": 30
  }
]
